kdp_api/__init__.py
kdp_api/api_client.py
kdp_api/configuration.py
kdp_api/exceptions.py
kdp_api/model_utils.py
kdp_api/rest.py
kdp_api/api/__init__.py
kdp_api/api/abac_label_parsers_api.py
kdp_api/api/applications_api.py
kdp_api/api/attribute_assignments_api.py
kdp_api/api/attributes_api.py
kdp_api/api/audit_log_api.py
kdp_api/api/audit_log_configs_api.py
kdp_api/api/authentication_api.py
kdp_api/api/dataset_permissions_api.py
kdp_api/api/datasets_api.py
kdp_api/api/group_memberships_api.py
kdp_api/api/groups_api.py
kdp_api/api/indexes_api.py
kdp_api/api/ingest_api.py
kdp_api/api/jobs_api.py
kdp_api/api/query_api.py
kdp_api/api/read_api.py
kdp_api/api/reindex_api.py
kdp_api/api/segments_api.py
kdp_api/api/source_types_api.py
kdp_api/api/storage_api.py
kdp_api/api/transfer_resource_requests_api.py
kdp_api/api/users_api.py
kdp_api/api/workspace_invitations_api.py
kdp_api/api/workspace_management_api.py
kdp_api/api/workspaces_api.py
kdp_api/api/write_api.py
kdp_api/apis/__init__.py
kdp_api/model/__init__.py
kdp_api/model/abac_label_parser_paginator.py
kdp_api/model/abac_label_parsers.py
kdp_api/model/abac_label_parsers_list.py
kdp_api/model/api_error.py
kdp_api/model/application.py
kdp_api/model/application_create_request.py
kdp_api/model/application_list.py
kdp_api/model/application_paginator.py
kdp_api/model/application_patch_request.py
kdp_api/model/application_required_dataset_access.py
kdp_api/model/application_update_request.py
kdp_api/model/applications_required_dataset_access.py
kdp_api/model/attribute.py
kdp_api/model/attribute_assignment.py
kdp_api/model/attribute_assignment_create_request.py
kdp_api/model/attribute_assignment_list.py
kdp_api/model/attribute_assignment_paginator.py
kdp_api/model/attribute_assignment_patch_request.py
kdp_api/model/attribute_assignment_update_request.py
kdp_api/model/attribute_create_request.py
kdp_api/model/attribute_list.py
kdp_api/model/attribute_paginator.py
kdp_api/model/attribute_patch_request.py
kdp_api_python_client_internal-4.53.0.dist-info/METADATA
kdp_api_python_client_internal-4.53.0.dist-info/WHEEL
kdp_api_python_client_internal-4.53.0.dist-info/top_level.txt
kdp_api_python_client_internal-4.53.0.dist-info/RECORD
