Metadata-Version: 2.1
Name: kdp-api-python-client-internal
Version: 4.53.0
Summary: Koverse Data Platform (KDP) API
Home-page: UNKNOWN
Author: OpenAPI Generator community
Author-email: team@openapitools.org
License: UNKNOWN
Keywords: OpenAPI,OpenAPI-Generator,Koverse Data Platform (KDP) API
Platform: UNKNOWN
Requires-Python: >=3.6
Requires-Dist: python-dateutil
Requires-Dist: urllib3 (>=1.25.3)
